{
	"$schema": "http://schema.management.azure.com/schemas/2015-01-01/deploymentTemplate.json#",
	"contentVersion": "1.0.0.0",
	"parameters": {
		"factoryName": {
			"type": "string",
			"metadata": "Data Factory name",
			"defaultValue": "Chicago"
		}
	},
	"variables": {
		"factoryId": "[concat('Microsoft.DataFactory/factories/', parameters('factoryName'))]"
	},
	"resources": [
		{
			"name": "[concat(parameters('factoryName'), '/RestServiceTraffic')]",
			"type": "Microsoft.DataFactory/factories/linkedServices",
			"apiVersion": "2018-06-01",
			"properties": {
				"parameters": {
					"currentTime": {
						"type": "string"
					}
				},
				"annotations": [],
				"type": "RestService",
				"typeProperties": {
					"url": "https://data.cityofchicago.org/resource/kf7e-cur8.json?$$app_token=30TDJtjsfHEEq1VbQq22pNhzy&$select=time, region_id, speed, region, bus_count&$limit=2000&$where=time < @linkedService().currentTime",
					"enableServerCertificateValidation": true,
					"authenticationType": "Anonymous"
				}
			},
			"dependsOn": []
		}
	]
}